hintify.py
hintify-0.1.2.data/data/share/hintify/LICENSE
hintify-0.1.2.data/data/share/hintify/README.md
hintify-0.1.2.data/data/share/hintify/logo.png
hintify-0.1.2.data/data/share/hintify/requirements.txt
hintify-0.1.2.data/data/share/hintify/screenshot-64.png
hintify-0.1.2.data/data/share/hintify/settings-94.png
hintify-0.1.2.dist-info/licenses/LICENSE
hintify-0.1.2.dist-info/METADATA
hintify-0.1.2.dist-info/WHEEL
hintify-0.1.2.dist-info/entry_points.txt
hintify-0.1.2.dist-info/top_level.txt
hintify-0.1.2.dist-info/RECORD
