Metadata-Version: 2.4
Name: hintify
Version: 0.1.2
Summary: SnapAssist AI – real-time clipboard-to-hints assistant
Author: Hintify Contributors
License-Expression: MIT
Project-URL: Homepage, https://github.com/AryanVBW/Hintify
Keywords: education,ocr,ai,ollama,gemini,hints
Classifier: Programming Language :: Python :: 3
Classifier: Operating System :: OS Independent
Classifier: Intended Audience :: Education
Classifier: Topic :: Education
Requires-Python: >=3.9
License-File: LICENSE
Requires-Dist: pillow
Requires-Dist: pytesseract
Requires-Dist: keyring
Requires-Dist: requests
Requires-Dist: google-generativeai
Requires-Dist: pynput
Dynamic: license-file
